<http-page executeResourcesDynamically="false"
    forceEncodingForDynamicResources="false"
    name="/api/v1/notifications/count" playRequestsSequentially="false"
    recordedArtifactZipFileName="team/vus/@r3_@wetlink/%resources%/recorded-artifacts/f2a7f2bc-ad0d-4177-ba16-c1b237a912ff.zip"
    slaProfileEnabled="false" thinkTime="0"
    thinkTimeMode="MODE_SIMPLE_THINK_TIME" thinkTimeRangeEnd=""
    thinkTimeRangeStart="" uid="f2a7f2bc-ad0d-4177-ba16-c1b237a912ff">
    <embedded-action>b2c7ee71-8a2a-4427-9a48-40209c69f00d</embedded-action>
    <embedded-action>6b591fbb-1dc8-40b4-8964-3fa395a47fe1</embedded-action>
    <embedded-action>b8847ed3-259d-4754-a3f7-d033f0955635</embedded-action>
</http-page>
<http-action actionType="1" contentType="application/json"
    extractorInjectPathPolicy="2" extractorPathPolicy="1"
    followRedirects="false" generatedByClient="false"
    linkExtractorSeveralMatchOccurrence="1"
    linkExtractorSeveralMatchPolicy="1" linkExtractorType="6"
    method="GET" name="/api/v1/notifications/count"
    path="/api/v1/notifications/count" postType="6"
    recordedArtifactZipFileName="team/vus/@r3_@wetlink/%resources%/recorded-artifacts/f2a7f2bc-ad0d-4177-ba16-c1b237a912ff.zip"
    recordedResponseCode="200" responseSize="46"
    serverUid="uat-dcp.sla.gov.sg" slaProfileEnabled="false"
    uid="b2c7ee71-8a2a-4427-9a48-40209c69f00d" useKeepAlive="false">
    <responsePageFileDescription>recorded-responses/res_72c3f472-3389-442b-a6d4-1ddad2440944</responsePageFileDescription>
    <requestContentFileDescription>recorded-requests/req_72c3f472-3389-442b-a6d4-1ddad2440944.txt</requestContentFileDescription>
    <parameter encodeName="true" encodeValue="false" name="search"
        recordRawValue="deliveryModeCode=SYSTEMNOTIFY" separator="="
        value="deliveryModeCode=SYSTEMNOTIFY" valueMode="USE_VALUE"/>
    <header name="Accept" value="application/json, text/plain, */*"/>
    <header name="Accept-Encoding" value="gzip, deflate, br, zstd"/>
    <header name="Accept-Language" value="en-US,en;q=0.9"/>
    <header name="Authorization" value="Bearer ${C_token7}"/>
    <header name="Connection" value="keep-alive"/>
    <header name="Host" value="uat-dcp.sla.gov.sg"/>
    <header name="Referer" value="https://uat-dcp.sla.gov.sg/wetInkProperty"/>
    <header name="sec-ch-ua" value="&quot;Google Chrome&quot;;v=&quot;137&quot;, &quot;Chromium&quot;;v=&quot;137&quot;, &quot;Not/A)Brand&quot;;v=&quot;24&quot;"/>
    <header name="sec-ch-ua-mobile" value="?0"/>
    <header name="sec-ch-ua-platform" value="&quot;Windows&quot;"/>
    <header name="Sec-Fetch-Dest" value="empty"/>
    <header name="Sec-Fetch-Mode" value="cors"/>
    <header name="Sec-Fetch-Site" value="same-origin"/>
    <header name="User-Agent" value="Mozilla/5.0 (Windows NT 10.0; Win64; x64) AppleWebKit/537.36 (KHTML, like Gecko) Chrome/137.0.0.0 Safari/537.36"/>
    <responseHeaders>HTTP/1.1 200 &#xd;
Content-Type: application/json&#xd;
Transfer-Encoding: chunked&#xd;
Connection: keep-alive&#xd;
Date: Thu, 05 Jun 2025 04:54:33 GMT&#xd;
Strict-Transport-Security: max-age=31536000 ; includeSubDomains&#xd;
X-Frame-Options: DENY&#xd;
Vary: Origin&#xd;
Vary: Access-Control-Request-Method&#xd;
Vary: Access-Control-Request-Headers&#xd;
X-Content-Type-Options: nosniff&#xd;
X-XSS-Protection: 0&#xd;
Cache-Control: no-cache, no-store, max-age=0, must-revalidate&#xd;
Pragma: no-cache&#xd;
Expires: 0&#xd;
X-Cache: Miss from cloudfront&#xd;
Via: 1.1 aa27a00d18f5fd7fe6d6c8f067b321d6.cloudfront.net (CloudFront)&#xd;
X-Amz-Cf-Pop: SIN2-P4&#xd;
X-Amz-Cf-Id: 8SPWhOCkvlUgfYiqfUBQwM2QtCJpwrda5BbeLazkfzafKZgASqQbJg==</responseHeaders>
    <record-html-infos extractorRegExp="false" htmlType="0"/>
</http-action>
<http-action actionType="1" contentType="application/json"
    extractorInjectPathPolicy="2" extractorPathPolicy="1"
    followRedirects="false" generatedByClient="false"
    linkExtractorSeveralMatchOccurrence="1"
    linkExtractorSeveralMatchPolicy="1" linkExtractorType="6"
    method="GET" name="/api/v1/announcements"
    path="/api/v1/announcements" postType="6"
    recordedArtifactZipFileName="team/vus/@r3_@wetlink/%resources%/recorded-artifacts/f2a7f2bc-ad0d-4177-ba16-c1b237a912ff.zip"
    recordedResponseCode="200" responseSize="52"
    serverUid="uat-dcp.sla.gov.sg" slaProfileEnabled="false"
    uid="6b591fbb-1dc8-40b4-8964-3fa395a47fe1" useKeepAlive="false">
    <responsePageFileDescription>recorded-responses/res_9f429613-5b3f-44e0-a4fa-d859e6ab2d93</responsePageFileDescription>
    <requestContentFileDescription>recorded-requests/req_9f429613-5b3f-44e0-a4fa-d859e6ab2d93.txt</requestContentFileDescription>
    <parameter encodeName="true" encodeValue="false" name="page"
        recordRawValue="dashboard,all" separator="="
        value="dashboard,all" valueMode="USE_VALUE"/>
    <header name="Accept" value="application/json, text/plain, */*"/>
    <header name="Accept-Encoding" value="gzip, deflate, br, zstd"/>
    <header name="Accept-Language" value="en-US,en;q=0.9"/>
    <header name="Authorization" value="Bearer ${C_token7}"/>
    <header name="Connection" value="keep-alive"/>
    <header name="Host" value="uat-dcp.sla.gov.sg"/>
    <header name="Referer" value="https://uat-dcp.sla.gov.sg/wetInkProperty"/>
    <header name="sec-ch-ua" value="&quot;Google Chrome&quot;;v=&quot;137&quot;, &quot;Chromium&quot;;v=&quot;137&quot;, &quot;Not/A)Brand&quot;;v=&quot;24&quot;"/>
    <header name="sec-ch-ua-mobile" value="?0"/>
    <header name="sec-ch-ua-platform" value="&quot;Windows&quot;"/>
    <header name="Sec-Fetch-Dest" value="empty"/>
    <header name="Sec-Fetch-Mode" value="cors"/>
    <header name="Sec-Fetch-Site" value="same-origin"/>
    <header name="User-Agent" value="Mozilla/5.0 (Windows NT 10.0; Win64; x64) AppleWebKit/537.36 (KHTML, like Gecko) Chrome/137.0.0.0 Safari/537.36"/>
    <responseHeaders>HTTP/1.1 200 &#xd;
Content-Type: application/json&#xd;
Transfer-Encoding: chunked&#xd;
Connection: keep-alive&#xd;
Date: Thu, 05 Jun 2025 04:54:33 GMT&#xd;
Strict-Transport-Security: max-age=31536000 ; includeSubDomains&#xd;
X-Frame-Options: DENY&#xd;
Vary: Origin&#xd;
Vary: Access-Control-Request-Method&#xd;
Vary: Access-Control-Request-Headers&#xd;
X-Content-Type-Options: nosniff&#xd;
X-XSS-Protection: 0&#xd;
Cache-Control: no-cache, no-store, max-age=0, must-revalidate&#xd;
Pragma: no-cache&#xd;
Expires: 0&#xd;
X-Cache: Miss from cloudfront&#xd;
Via: 1.1 2f37710b411dfd57a465b8ca27d41bee.cloudfront.net (CloudFront)&#xd;
X-Amz-Cf-Pop: SIN2-P4&#xd;
X-Amz-Cf-Id: K49TynEsiM6_fLToHTo6wuVy6YuhCBf3N52sTsgHSEXR1cfHsNXvpw==</responseHeaders>
    <record-html-infos extractorRegExp="false" htmlType="0"/>
</http-action>
<http-action actionType="1" contentType="application/json"
    extractorInjectPathPolicy="2" extractorPathPolicy="1"
    followRedirects="false" generatedByClient="false"
    linkExtractorSeveralMatchOccurrence="1"
    linkExtractorSeveralMatchPolicy="1" linkExtractorType="6"
    method="GET"
    name="/api/v1/users/de183c13-b4de-4c4d-bef0-daea3acdf805"
    path="/api/v1/users/${C_userId_VL}" postType="6"
    recordedArtifactZipFileName="team/vus/@r3_@wetlink/%resources%/recorded-artifacts/f2a7f2bc-ad0d-4177-ba16-c1b237a912ff.zip"
    recordedResponseCode="200" responseSize="1030"
    serverUid="uat-dcp.sla.gov.sg" slaProfileEnabled="false"
    uid="b8847ed3-259d-4754-a3f7-d033f0955635" useKeepAlive="false">
    <responsePageFileDescription>recorded-responses/res_75fd8c70-6b30-4313-8327-097a38585ab2</responsePageFileDescription>
    <requestContentFileDescription>recorded-requests/req_75fd8c70-6b30-4313-8327-097a38585ab2.txt</requestContentFileDescription>
    <variable-extractor assertionOnNoMatch="true"
        defaultValue="&lt;NOT FOUND>" displayMode="0"
        endsWithSimple="&quot;" extractFromVarNameAdv=""
        extractFromVarNameSimple="" extractType="0" extractTypeAdv="0"
        extractTypeSimple="0" matchNumber="1" matchNumberAdv="1"
        matchNumberSimple="1" name="C_name_VL"
        refererUid="71d9b7d1-1801-414b-a567-d4276f3d45da"
        regExp="&quot;name&quot;:&quot;(.*?)&quot;" regExpAdv=""
        setDefaultValue="true"
        startsWithSimple="&quot;name&quot;:&quot;" template="$1$"
        templateAdv="$1$" uid="ef46b650-b546-4824-9f42-8d3ea74d8d56" xpath="">
        <variable-extractor-group extract="true" occurs="1" pattern="" type="4"/>
    </variable-extractor>
    <variable-extractor assertionOnNoMatch="true"
        defaultValue="&lt;NOT FOUND>" displayMode="0"
        endsWithSimple="&quot;" extractFromVarNameAdv=""
        extractFromVarNameSimple="" extractType="0" extractTypeAdv="0"
        extractTypeSimple="0" matchNumber="1" matchNumberAdv="1"
        matchNumberSimple="1" name="C_identificationNo_VL"
        refererUid="71d9b7d1-1801-414b-a567-d4276f3d45da"
        regExp="&quot;uen&quot;:&quot;(.*?)&quot;" regExpAdv=""
        setDefaultValue="true" startsWithSimple="&quot;uen&quot;:&quot;"
        template="$1$" templateAdv="$1$"
        uid="333fc404-6ad6-41e3-9768-8f76e271abb7" xpath="">
        <variable-extractor-group extract="true" occurs="1" pattern="" type="4"/>
    </variable-extractor>
    <variable-extractor assertionOnNoMatch="true"
        defaultValue="&lt;NOT FOUND>" displayMode="0"
        endsWithSimple="&quot;" extractFromVarNameAdv=""
        extractFromVarNameSimple="" extractType="0" extractTypeAdv="0"
        extractTypeSimple="0" matchNumber="1" matchNumberAdv="1"
        matchNumberSimple="1" name="C_emailAddress_VL"
        refererUid="71d9b7d1-1801-414b-a567-d4276f3d45da"
        regExp="&quot;emailAddress&quot;:&quot;(.*?)&quot;" regExpAdv=""
        setDefaultValue="true"
        startsWithSimple="&quot;emailAddress&quot;:&quot;"
        template="$1$" templateAdv="$1$"
        uid="05c1a2d0-cc4c-4ad3-bc54-70efebc005fa" xpath="">
        <variable-extractor-group extract="true" occurs="1" pattern="" type="4"/>
    </variable-extractor>
    <variable-extractor assertionOnNoMatch="true"
        defaultValue="&lt;NOT FOUND>" displayMode="0"
        endsWithSimple="&quot;" extractFromVarNameAdv=""
        extractFromVarNameSimple="" extractType="0" extractTypeAdv="0"
        extractTypeSimple="0" matchNumber="1" matchNumberAdv="1"
        matchNumberSimple="1" name="C_companyId_VL"
        refererUid="71d9b7d1-1801-414b-a567-d4276f3d45da"
        regExp="&quot;companyId&quot;:&quot;(.*?)&quot;" regExpAdv=""
        setDefaultValue="true"
        startsWithSimple="&quot;companyId&quot;:&quot;" template="$1$"
        templateAdv="$1$" uid="16086271-8560-453e-b684-b5e542007519" xpath="">
        <variable-extractor-group extract="true" occurs="1" pattern="" type="4"/>
    </variable-extractor>
    <variable-extractor assertionOnNoMatch="true"
        defaultValue="&lt;NOT FOUND>" displayMode="0"
        endsWithSimple="&quot;" extractFromVarNameAdv=""
        extractFromVarNameSimple="" extractType="0" extractTypeAdv="0"
        extractTypeSimple="0" matchNumber="1" matchNumberAdv="1"
        matchNumberSimple="1" name="C_UserId_VL"
        refererUid="b8847ed3-259d-4754-a3f7-d033f0955635"
        regExp="userId&quot;:&quot;(.*?)&quot;" regExpAdv=""
        setDefaultValue="true" startsWithSimple="userId&quot;:&quot;"
        template="$1$" templateAdv="$1$"
        uid="db0e8853-f9ed-40b4-b306-be839d6af9fc" xpath="">
        <variable-extractor-group extract="true" occurs="1" pattern="" type="4"/>
    </variable-extractor>
    <header name="Accept" value="application/json, text/plain, */*"/>
    <header name="Accept-Encoding" value="gzip, deflate, br, zstd"/>
    <header name="Accept-Language" value="en-US,en;q=0.9"/>
    <header name="Authorization" value="Bearer ${C_token7}"/>
    <header name="Connection" value="keep-alive"/>
    <header name="Host" value="uat-dcp.sla.gov.sg"/>
    <header name="Referer" value="https://uat-dcp.sla.gov.sg/wetInkProperty"/>
    <header name="sec-ch-ua" value="&quot;Google Chrome&quot;;v=&quot;137&quot;, &quot;Chromium&quot;;v=&quot;137&quot;, &quot;Not/A)Brand&quot;;v=&quot;24&quot;"/>
    <header name="sec-ch-ua-mobile" value="?0"/>
    <header name="sec-ch-ua-platform" value="&quot;Windows&quot;"/>
    <header name="Sec-Fetch-Dest" value="empty"/>
    <header name="Sec-Fetch-Mode" value="cors"/>
    <header name="Sec-Fetch-Site" value="same-origin"/>
    <header name="User-Agent" value="Mozilla/5.0 (Windows NT 10.0; Win64; x64) AppleWebKit/537.36 (KHTML, like Gecko) Chrome/137.0.0.0 Safari/537.36"/>
    <responseHeaders>HTTP/1.1 200 &#xd;
Content-Type: application/json&#xd;
Transfer-Encoding: chunked&#xd;
Connection: keep-alive&#xd;
Date: Thu, 05 Jun 2025 04:54:33 GMT&#xd;
Strict-Transport-Security: max-age=31536000 ; includeSubDomains&#xd;
X-Frame-Options: DENY&#xd;
Vary: Origin&#xd;
Vary: Access-Control-Request-Method&#xd;
Vary: Access-Control-Request-Headers&#xd;
X-Content-Type-Options: nosniff&#xd;
X-XSS-Protection: 0&#xd;
Cache-Control: no-cache, no-store, max-age=0, must-revalidate&#xd;
Pragma: no-cache&#xd;
Expires: 0&#xd;
X-Cache: Miss from cloudfront&#xd;
Via: 1.1 69ce12cd28f192f5e142ba57e5fe0b80.cloudfront.net (CloudFront)&#xd;
X-Amz-Cf-Pop: SIN2-P4&#xd;
X-Amz-Cf-Id: w3rmg01Crd77ZvoyOPkkIWDS08yaRl6QN7i9l7EdwDrHt4WiECny1Q==</responseHeaders>
    <record-html-infos extractorRegExp="false" htmlType="0"/>
</http-action>
